{"analysis_type":"chronological_peripheral_access_sequence","chronological_sequence":[{"access_type":"volatile_read","address":"0x1074790400","basic_block_id":"GPIO_PinInit_BB_94369307430704","bits_modified":[],"call_stack":"GPIO_PinInit","data_size":32,"execution_context":"driver_initialization","execution_phase":"driver_init","instruction_index":5,"peripheral_name":"GPIO0","purpose":"Initialize GPIO0 controller","register_name":"PDOR","sequence_number":0,"source_location":{"file":"mimxrt700evk_xspi_psram_polling_transfer_cm33_core0/__repo__/devices/MIMXRT798S/drivers/fsl_gpio.c","function":"GPIO_PinInit","line":198}},{"access_type":"volatile_write","address":"0x1074790400","basic_block_id":"GPIO_PinInit_BB_94369307430704","bits_modified":["bit_0-31"],"call_stack":"GPIO_PinInit","data_size":32,"execution_context":"driver_initialization","execution_phase":"driver_init","instruction_index":7,"peripheral_name":"GPIO0","purpose":"Initialize GPIO0 controller","register_name":"PDOR","sequence_number":1,"source_location":{"file":"mimxrt700evk_xspi_psram_polling_transfer_cm33_core0/__repo__/devices/MIMXRT798S/drivers/fsl_gpio.c","function":"GPIO_PinInit","line":198}},{"access_type":"volatile_read","address":"0x1074790400","basic_block_id":"GPIO_PinInit_BB_94369307430864","bits_modified":[],"call_stack":"GPIO_PinInit","data_size":32,"execution_context":"driver_initialization","execution_phase":"driver_init","instruction_index":10,"peripheral_name":"GPIO0","purpose":"Initialize GPIO0 controller","register_name":"PDOR","sequence_number":2,"source_location":{"file":"mimxrt700evk_xspi_psram_polling_transfer_cm33_core0/__repo__/devices/MIMXRT798S/drivers/fsl_gpio.c","function":"GPIO_PinInit","line":203}},{"access_type":"volatile_write","address":"0x1074790400","basic_block_id":"GPIO_PinInit_BB_94369307430864","bits_modified":["bit_0-31"],"call_stack":"GPIO_PinInit","data_size":32,"execution_context":"driver_initialization","execution_phase":"driver_init","instruction_index":12,"peripheral_name":"GPIO0","purpose":"Initialize GPIO0 controller","register_name":"PDOR","sequence_number":3,"source_location":{"file":"mimxrt700evk_xspi_psram_polling_transfer_cm33_core0/__repo__/devices/MIMXRT798S/drivers/fsl_gpio.c","function":"GPIO_PinInit","line":203}},{"access_type":"volatile_write","address":"0x1074790400","basic_block_id":"GPIO_PinWrite_BB_94369307403536","bits_modified":["bit_0-31"],"call_stack":"GPIO_PinWrite","data_size":32,"execution_context":"runtime_operation","execution_phase":"runtime","instruction_index":4,"peripheral_name":"GPIO0","purpose":"Write data to GPIO0","register_name":"PDOR","sequence_number":4,"source_location":{"file":"mimxrt700evk_xspi_psram_polling_transfer_cm33_core0/__repo__/devices/MIMXRT798S/drivers/fsl_gpio.h","function":"GPIO_PinWrite","line":350}},{"access_type":"volatile_write","address":"0x1074790400","basic_block_id":"GPIO_PinWrite_BB_94369307459616","bits_modified":["bit_0-31"],"call_stack":"GPIO_PinWrite","data_size":32,"execution_context":"runtime_operation","execution_phase":"runtime","instruction_index":4,"peripheral_name":"GPIO0","purpose":"Write data to GPIO0","register_name":"PDOR","sequence_number":5,"source_location":{"file":"mimxrt700evk_xspi_psram_polling_transfer_cm33_core0/__repo__/devices/MIMXRT798S/drivers/fsl_gpio.h","function":"GPIO_PinWrite","line":354}},{"access_type":"volatile_read","address":"0x1074790400","basic_block_id":"GPIO_GetVersionInfo_BB_94369307469280","bits_modified":[],"call_stack":"GPIO_GetVersionInfo","data_size":32,"execution_context":"status_monitoring","execution_phase":"runtime","instruction_index":7,"peripheral_name":"GPIO0","purpose":"Access PDOR register","register_name":"PDOR","sequence_number":6,"source_location":{"file":"mimxrt700evk_xspi_psram_polling_transfer_cm33_core0/__repo__/devices/MIMXRT798S/drivers/fsl_gpio.c","function":"GPIO_GetVersionInfo","line":210}},{"access_type":"volatile_read","address":"0x1074790400","basic_block_id":"GPIO_GpioGetInterruptFlags_BB_94369307492992","bits_modified":[],"call_stack":"GPIO_GpioGetInterruptFlags","data_size":32,"execution_context":"status_monitoring","execution_phase":"runtime","instruction_index":5,"peripheral_name":"GPIO0","purpose":"Access PDOR register","register_name":"PDOR","sequence_number":7,"source_location":{"file":"mimxrt700evk_xspi_psram_polling_transfer_cm33_core0/__repo__/devices/MIMXRT798S/drivers/fsl_gpio.c","function":"GPIO_GpioGetInterruptFlags","line":251}},{"access_type":"volatile_read","address":"0x1074790400","basic_block_id":"GPIO_GpioGetInterruptChannelFlags_BB_94369307508160","bits_modified":[],"call_stack":"GPIO_GpioGetInterruptChannelFlags","data_size":32,"execution_context":"status_monitoring","execution_phase":"runtime","instruction_index":4,"peripheral_name":"GPIO0","purpose":"Access PDOR register","register_name":"PDOR","sequence_number":8,"source_location":{"file":"mimxrt700evk_xspi_psram_polling_transfer_cm33_core0/__repo__/devices/MIMXRT798S/drivers/fsl_gpio.c","function":"GPIO_GpioGetInterruptChannelFlags","line":266}},{"access_type":"volatile_read","address":"0x1074790400","basic_block_id":"GPIO_PinGetInterruptFlag_BB_94369307513568","bits_modified":[],"call_stack":"GPIO_PinGetInterruptFlag","data_size":32,"execution_context":"status_monitoring","execution_phase":"runtime","instruction_index":8,"peripheral_name":"GPIO0","purpose":"Access PDOR register","register_name":"PDOR","sequence_number":9,"source_location":{"file":"mimxrt700evk_xspi_psram_polling_transfer_cm33_core0/__repo__/devices/MIMXRT798S/drivers/fsl_gpio.c","function":"GPIO_PinGetInterruptFlag","line":278}},{"access_type":"volatile_write","address":"0x1074790400","basic_block_id":"GPIO_GpioClearInterruptFlags_BB_94369307525152","bits_modified":["bit_0-31"],"call_stack":"GPIO_GpioClearInterruptFlags","data_size":32,"execution_context":"runtime_operation","execution_phase":"runtime","instruction_index":8,"peripheral_name":"GPIO0","purpose":"Access PDOR register","register_name":"PDOR","sequence_number":10,"source_location":{"file":"mimxrt700evk_xspi_psram_polling_transfer_cm33_core0/__repo__/devices/MIMXRT798S/drivers/fsl_gpio.c","function":"GPIO_GpioClearInterruptFlags","line":307}},{"access_type":"volatile_write","address":"0x1074790400","basic_block_id":"GPIO_GpioClearInterruptChannelFlags_BB_94369307547456","bits_modified":["bit_0-31"],"call_stack":"GPIO_GpioClearInterruptChannelFlags","data_size":32,"execution_context":"runtime_operation","execution_phase":"runtime","instruction_index":5,"peripheral_name":"GPIO0","purpose":"Access PDOR register","register_name":"PDOR","sequence_number":11,"source_location":{"file":"mimxrt700evk_xspi_psram_polling_transfer_cm33_core0/__repo__/devices/MIMXRT798S/drivers/fsl_gpio.c","function":"GPIO_GpioClearInterruptChannelFlags","line":320}},{"access_type":"volatile_read","address":"0x1074790400","basic_block_id":"GPIO_PinClearInterruptFlag_BB_94369307553520","bits_modified":[],"call_stack":"GPIO_PinClearInterruptFlag","data_size":32,"execution_context":"status_monitoring","execution_phase":"runtime","instruction_index":8,"peripheral_name":"GPIO0","purpose":"Access PDOR register","register_name":"PDOR","sequence_number":12,"source_location":{"file":"mimxrt700evk_xspi_psram_polling_transfer_cm33_core0/__repo__/devices/MIMXRT798S/drivers/fsl_gpio.c","function":"GPIO_PinClearInterruptFlag","line":331}},{"access_type":"volatile_write","address":"0x1074790400","basic_block_id":"GPIO_PinClearInterruptFlag_BB_94369307553520","bits_modified":["bit_24"],"call_stack":"GPIO_PinClearInterruptFlag","data_size":32,"execution_context":"runtime_operation","execution_phase":"runtime","instruction_index":10,"peripheral_name":"GPIO0","purpose":"Access PDOR register","register_name":"PDOR","sequence_number":13,"source_location":{"file":"mimxrt700evk_xspi_psram_polling_transfer_cm33_core0/__repo__/devices/MIMXRT798S/drivers/fsl_gpio.c","function":"GPIO_PinClearInterruptFlag","line":331}}],"description":"Peripheral register accesses in chronological execution order","execution_phase_summary":{"driver_init":4,"runtime":10},"total_accesses":14}
